pycast/__init__.py
pycast/ecc.py
pycast/sbox.py
pycastx-0.1.1.dist-info/licenses/LICENCE
pycastx-0.1.1.dist-info/METADATA
pycastx-0.1.1.dist-info/WHEEL
pycastx-0.1.1.dist-info/top_level.txt
pycastx-0.1.1.dist-info/RECORD
