Metadata-Version: 2.4
Name: pycastx
Version: 0.1.1
Summary: Elliptic Curve Cryptography and Genetic AES S-Box Optimizer
Home-page: https://github.com/ahwarkhan/pycast
Author: Ahwar Khan
Author-email: khanahwar4@gmail.com
Classifier: Programming Language :: Python :: 3
Classifier: License :: OSI Approved :: MIT License
Requires-Python: >=3.7
License-File: LICENCE
Requires-Dist: numpy
Dynamic: author
Dynamic: author-email
Dynamic: classifier
Dynamic: description
Dynamic: description-content-type
Dynamic: home-page
Dynamic: license-file
Dynamic: requires-dist
Dynamic: requires-python
Dynamic: summary
